sacroml/__init__.py
sacroml/main.py
sacroml/metrics.py
sacroml/version.py
sacroml/attacks/__init__.py
sacroml/attacks/attack.py
sacroml/attacks/attack_report_formatter.py
sacroml/attacks/attribute_attack.py
sacroml/attacks/data.py
sacroml/attacks/factory.py
sacroml/attacks/likelihood_attack.py
sacroml/attacks/model.py
sacroml/attacks/model_pytorch.py
sacroml/attacks/model_sklearn.py
sacroml/attacks/report.py
sacroml/attacks/structural_attack.py
sacroml/attacks/target.py
sacroml/attacks/utils.py
sacroml/attacks/worst_case_attack.py
sacroml/config/__init__.py
sacroml/config/attack.py
sacroml/config/target.py
sacroml/config/utils.py
sacroml/safemodel/__init__.py
sacroml/safemodel/reporting.py
sacroml/safemodel/rules.json
sacroml/safemodel/safemodel.py
sacroml/safemodel/classifiers/__init__.py
sacroml/safemodel/classifiers/dp_svc.py
sacroml/safemodel/classifiers/new_model_template.py
sacroml/safemodel/classifiers/safedecisiontreeclassifier.py
sacroml/safemodel/classifiers/saferandomforestclassifier.py
sacroml/safemodel/classifiers/safesvc.py
sacroml-1.4.3.dist-info/licenses/LICENSE
sacroml-1.4.3.dist-info/METADATA
sacroml-1.4.3.dist-info/WHEEL
sacroml-1.4.3.dist-info/entry_points.txt
sacroml-1.4.3.dist-info/top_level.txt
sacroml-1.4.3.dist-info/RECORD
