Metadata-Version: 2.4
Name: sacroml
Version: 1.4.3
Summary: Tools for the statistical disclosure control of machine learning models
Maintainer-email: Jim Smith <james.smith@uwe.ac.uk>
License: MIT
Project-URL: Homepage, https://github.com/AI-SDC/SACRO-ML
Project-URL: Changelog, https://github.com/AI-SDC/SACRO-ML/CHANGELOG.md
Project-URL: Documentation, https://ai-sdc.github.io/SACRO-ML/
Project-URL: Bug Tracker, https://github.com/AI-SDC/SACRO-ML/issues
Project-URL: Discussions, https://github.com/AI-SDC/SACRO-ML/discussions
Keywords: data-privacy,data-protection,machine-learning,privacy,privacy-tools,statistical-disclosure-control
Classifier: Development Status :: 5 - Production/Stable
Classifier: Intended Audience :: Developers
Classifier: Intended Audience :: Science/Research
Classifier: License :: OSI Approved :: MIT License
Classifier: Natural Language :: English
Classifier: Programming Language :: Python :: 3.10
Classifier: Programming Language :: Python :: 3.11
Classifier: Programming Language :: Python :: 3.12
Classifier: Programming Language :: Python :: 3.13
Classifier: Programming Language :: Python :: 3.14
Classifier: Topic :: Scientific/Engineering
Classifier: Topic :: Scientific/Engineering :: Artificial Intelligence
Classifier: Topic :: Scientific/Engineering :: Information Analysis
Classifier: Operating System :: OS Independent
Requires-Python: >=3.10
License-File: LICENSE
Requires-Dist: acro==0.4.11
Requires-Dist: fpdf
Requires-Dist: pypdf
Requires-Dist: multiprocess
Requires-Dist: scikit-learn
Requires-Dist: xgboost
Requires-Dist: dictdiffer
Requires-Dist: torch
Requires-Dist: prompt-toolkit
Provides-Extra: doc
Requires-Dist: numpydoc; extra == "doc"
Requires-Dist: sphinx-autopackagesummary; extra == "doc"
Requires-Dist: sphinx-issues; extra == "doc"
Requires-Dist: sphinx-prompt; extra == "doc"
Requires-Dist: sphinx; extra == "doc"
Requires-Dist: sphinxcontrib-bibtex; extra == "doc"
Requires-Dist: nbsphinx; extra == "doc"
Requires-Dist: ipykernel; extra == "doc"
Requires-Dist: pydata-sphinx-theme; extra == "doc"
Requires-Dist: sphinx-design; extra == "doc"
Requires-Dist: myst-parser; extra == "doc"
Provides-Extra: test
Requires-Dist: pytest; extra == "test"
Requires-Dist: pytest-cov; extra == "test"
Dynamic: license-file
